nandorapi/__init__.py
nandorapi/client.py
nandorapi/tools.py
nandorapi-0.0.1.dist-info/licenses/LICENSE
nandorapi-0.0.1.dist-info/METADATA
nandorapi-0.0.1.dist-info/WHEEL
nandorapi-0.0.1.dist-info/top_level.txt
nandorapi-0.0.1.dist-info/RECORD
