Metadata-Version: 2.4
Name: nandorapi
Version: 0.0.1
Summary: Relentless API client
Author-email: Peter Jachim <pjachim@outlook.com>
License-Expression: Apache-2.0
Project-URL: Homepage, https://github.com/pjachim/NandorAPI
Project-URL: Issues, https://github.com/pjachim/NandorAPI/issues
Classifier: Programming Language :: Python :: 3
Classifier: Operating System :: OS Independent
Requires-Python: >=3.10
License-File: LICENSE
Dynamic: license-file
